ciles/__init__.py
ciles/examples.py
ciles/integrator.so
ciles/tools.py
ciles-0.1.0.dist-info/DESCRIPTION.rst
ciles-0.1.0.dist-info/METADATA
ciles-0.1.0.dist-info/RECORD
ciles-0.1.0.dist-info/WHEEL
ciles-0.1.0.dist-info/metadata.json
ciles-0.1.0.dist-info/top_level.txt
tests/__init__.py
tests/test_diffusion.py
