Metadata-Version: 2.0
Name: ciles
Version: 0.1.0
Summary: Langevin integrator for SDEs with constant drift and        diffusion on continuous intervals with circular boundary        conditions.
Home-page: https://github.com/flinz/ciles
Author: Alex Seeholzer
Author-email: seeholzer@gmail.com
License: GPLv2
Keywords: science,langevin,math
Platform: UNKNOWN
Classifier: Development Status :: 3 - Alpha
Classifier: License :: OSI Approved :: GNU General Public License v2 (GPLv2)
Classifier: Programming Language :: Python :: 2.7
Classifier: Topic :: Scientific/Engineering :: Medical Science Apps.
Requires-Dist: cython
Requires-Dist: cythongsl
Requires-Dist: numpy
